{
  "type": "FeatureCollection",
  "features": [
    {
      "type": "Feature",
      "properties": {},
      "geometry": {
        "type": "Polygon",
        "coordinates": [
          [
            [
              113.54826629161835,
              22.21671835947633
            ],
            [
              113.54835748672485,
              22.21674319030022
            ],
            [
              113.54866325855255,
              22.21663393464221
            ],
            [
              113.54906558990479,
              22.216579306781306
            ],
            [
              113.54967713356017,
              22.21671835947633
            ],
            [
              113.55003118515015,
              22.2169219721025
            ],
            [
              113.55084121227264,
              22.21705109215134
            ],
            [
              113.55067491531372,
              22.21562579887382
            ],
            [
              113.55123013257979,
              22.215419701260778
            ],
            [
              113.55442464351654,
              22.214274984911132
            ],
            [
              113.55453729629517,
              22.21407136844317
            ],
            [
              113.55706930160521,
              22.213291663626247
            ],
            [
              113.55867862701416,
              22.212715573207365
            ],
            [
              113.5589200258255,
              22.21269570797833
            ],
            [
              113.55891466140747,
              22.212591415479697
            ],
            [
              113.55938673019408,
              22.212283503840965
            ],
            [
              113.55993390083313,
              22.211776938061863
            ],
            [
              113.56006264686584,
              22.21174217367663
            ],
            [
              113.56004655361176,
              22.211622981433294
            ],
            [
              113.56057494878767,
              22.210895409919335
            ],
            [
              113.56078684329987,
              22.210480717300314
            ],
            [
              113.56086194515228,
              22.210436019819117
            ],
            [
              113.56088072061539,
              22.210264679342593
            ],
            [
              113.56107652187347,
              22.209308645307335
            ],
            [
              113.56113284826279,
              22.208052133527218
            ],
            [
              113.56103897094725,
              22.207078701647795
            ],
            [
              113.5610282421112,
              22.207006687286455
            ],
            [
              113.56112748384476,
              22.20581472007635
            ],
            [
              113.56129378080368,
              22.204965437263517
            ],
            [
              113.56142789125443,
              22.20459542647775
            ],
            [
              113.56120526790619,
              22.20452837743903
            ],
            [
              113.56278777122498,
              22.19977278059782
            ],
            [
              113.5630452632904,
              22.199633711111844
            ],
            [
              113.5633134841919,
              22.19927610322968
            ],
            [
              113.56338858604431,
              22.198898627254785
            ],
            [
              113.56324911117554,
              22.19783572892632
            ],
            [
              113.56335639953612,
              22.197378779508323
            ],
            [
              113.56361389160156,
              22.167733493573387
            ],
            [
              113.56368362903595,
              22.16719695961653
            ],
            [
              113.56394648551941,
              22.166849205032616
            ],
            [
              113.564413189888,
              22.16654616105114
            ],
            [
              113.56459021568298,
              22.166297763858026
            ],
            [
              113.56458485126494,
              22.16602949439667
            ],
            [
              113.56442928314209,
              22.165771160357654
            ],
            [
              113.56397867202757,
              22.165408498309887
            ],
            [
              113.5656201839447,
              22.164941507446333
            ],
            [
              113.56577038764954,
              22.165011059375335
            ],
            [
              113.56737971305847,
              22.16483221148838
            ],
            [
              113.56808781623839,
              22.164693107419076
            ],
            [
              113.56847405433655,
              22.166163629191324
            ],
            [
              113.57130646705627,
              22.165487985962017
            ],
            [
              113.57181072235107,
              22.167375804496253
            ],
            [
              113.57196092605591,
              22.167405611954102
            ],
            [
              113.5725724697113,
              22.16974050985318
            ],
            [
              113.57275485992432,
              22.16988954457297
            ],
            [
              113.57294797897339,
              22.169919351497963
            ],
            [
              113.57440710067749,
              22.169531860980094
            ],
            [
              113.57551217079163,
              22.171071881085687
            ],
            [
              113.57578039169312,
              22.17093278318844
            ],
            [
              113.57587695121765,
              22.170614844620893
            ],
            [
              113.57595205307007,
              22.170366454614765
            ],
            [
              113.5758125782013,
              22.17013793542158
            ],
            [
              113.57368826866148,
              22.16708766541138
            ],
            [
              113.57368826866148,
              22.166908820165204
            ],
            [
              113.5738706588745,
              22.166829333316127
            ],
            [
              113.57349514961243,
              22.165487985962017
            ],
            [
              113.57414960861206,
              22.165319074647538
            ],
            [
              113.57441782951355,
              22.16621330871242
            ],
            [
              113.57476115226746,
              22.166113949652658
            ],
            [
              113.57447147369385,
              22.165229650928325
            ],
            [
              113.57609152793884,
              22.16487195548292
            ],
            [
              113.57701420783995,
              22.16793220933421
            ],
            [
              113.57850551605225,
              22.16753477753173
            ],
            [
              113.57760429382324,
              22.16454406719213
            ],
            [
              113.57844114303589,
              22.164385090776
            ],
            [
              113.57889175415039,
              22.166074206009114
            ],
            [
              113.57908487319946,
              22.16602452643887
            ],
            [
              113.57866644859313,
              22.16452419514995
            ],
            [
              113.57890248298645,
              22.164484451057135
            ],
            [
              113.57862353324889,
              22.16351071727525
            ],
            [
              113.57848405838011,
              22.162745636003265
            ],
            [
              113.57987880706787,
              22.163192761927316
            ],
            [
              113.57944965362547,
              22.164236050222666
            ],
            [
              113.57948184013367,
              22.164385090776
            ],
            [
              113.58014702796936,
              22.165050803319325
            ],
            [
              113.58075857162474,
              22.1673360612093
            ],
            [
              113.57955694198608,
              22.170475746271524
            ],
            [
              113.57979297637938,
              22.170495617472714
            ],
            [
              113.58163833618164,
              22.165706576773747
            ],
            [
              113.5827112197876,
              22.166104013742817
            ],
            [
              113.58378410339355,
              22.16356039773344
            ],
            [
              113.5790205001831,
              22.162010359171102
            ],
            [
              113.57882738113402,
              22.161771890183925
            ],
            [
              113.57889175415039,
              22.16158310194905
            ],
            [
              113.58500719070435,
              22.1635504616432
            ],
            [
              113.58466386795044,
              22.16450432310495
            ],
            [
              113.58484625816345,
              22.16498125140997
            ],
            [
              113.5851788520813,
              22.165388626389827
            ],
            [
              113.58641266822815,
              22.165736384585387
            ],
            [
              113.58671307563782,
              22.165726448648883
            ],
            [
              113.58741044998169,
              22.16528926674744
            ],
            [
              113.59841823577881,
              22.13551795815209
            ],
            [
              113.59794616699219,
              22.134722910335515
            ],
            [
              113.59526395797728,
              22.133947734393697
            ],
            [
              113.594491481781,
              22.134504271399233
            ],
            [
              113.59025359153748,
              22.146002231368026
            ],
            [
              113.58973860740662,
              22.14607179265913
            ],
            [
              113.58932018280028,
              22.14721458037787
            ],
            [
              113.58958840370178,
              22.14756238349435
            ],
            [
              113.57673525810242,
              22.155462251390688
            ],
            [
              113.57669234275816,
              22.155144277852195
            ],
            [
              113.57616662979125,
              22.154597759154107
            ],
            [
              113.57568383216856,
              22.154041301571617
            ],
            [
              113.57404232025146,
              22.152988000837432
            ],
            [
              113.57404232025146,
              22.15269983228197
            ],
            [
              113.57417106628417,
              22.15267002170808
            ],
            [
              113.57445001602173,
              22.153017811343982
            ],
            [
              113.57623100280762,
              22.154259910170012
            ],
            [
              113.57744336128235,
              22.153991617751885
            ],
            [
              113.5876679420471,
              22.147701504500326
            ],
            [
              113.58786106109619,
              22.14607179265913
            ],
            [
              113.58693838119507,
              22.145674299104137
            ],
            [
              113.58676671981812,
              22.145316553945058
            ],
            [
              113.58687400817871,
              22.144938933068683
            ],
            [
              113.58706712722778,
              22.144322812622267
            ],
            [
              113.58805418014526,
              22.143428439434608
            ],
            [
              113.58792543411255,
              22.142931562986572
            ],
            [
              113.58747482299805,
              22.142871937694974
            ],
            [
              113.58704566955565,
              22.143090563640715
            ],
            [
              113.58650922775269,
              22.142772562152867
            ],
            [
              113.58620882034302,
              22.142951438078164
            ],
            [
              113.58601570129393,
              22.14360731452665
            ],
            [
              113.58565092086792,
              22.144004813917572
            ],
            [
              113.58496427536011,
              22.14420356319218
            ],
            [
              113.58485698699951,
              22.14374643944112
            ],
            [
              113.58464241027832,
              22.14354768952123
            ],
            [
              113.58395576477051,
              22.143984938974675
            ],
            [
              113.58371973037718,
              22.143945189080476
            ],
            [
              113.58305454254149,
              22.144124063516013
            ],
            [
              113.58307600021361,
              22.144461936829714
            ],
            [
              113.58331203460693,
              22.1447203099931
            ],
            [
              113.58230352401733,
              22.144740184832184
            ],
            [
              113.58129501342773,
              22.144124063516013
            ],
            [
              113.57964277267456,
              22.14424331301343
            ],
            [
              113.57934236526489,
              22.14454143631511
            ],
            [
              113.57925653457642,
              22.144938933068683
            ],
            [
              113.57855647802353,
              22.144807262393368
            ],
            [
              113.5780656337738,
              22.14463335753914
            ],
            [
              113.57779204845428,
              22.144670622883126
            ],
            [
              113.57758283615112,
              22.144745153541514
            ],
            [
              113.57736825942993,
              22.144419702709843
            ],
            [
              113.57697933912277,
              22.144116610419065
            ],
            [
              113.5770571231842,
              22.143766314417693
            ],
            [
              113.57758283615112,
              22.143319126766492
            ],
            [
              113.57764720916748,
              22.143140251308317
            ],
            [
              113.5777223110199,
              22.143130313776204
            ],
            [
              113.57785105705261,
              22.14297131316693
            ],
            [
              113.5778295993805,
              22.14267318654062
            ],
            [
              113.57794761657715,
              22.142076931394243
            ],
            [
              113.57759356498718,
              22.140606157904593
            ],
            [
              113.57692837715149,
              22.139622321117123
            ],
            [
              113.57650995254515,
              22.138817358633023
            ],
            [
              113.57689619064331,
              22.138449658189643
            ],
            [
              113.57689619064331,
              22.138330403785613
            ],
            [
              113.5770034790039,
              22.138171397756484
            ],
            [
              113.57781887054442,
              22.138628539606334
            ],
            [
              113.57793688774109,
              22.13882729646953
            ],
            [
              113.5782265663147,
              22.13899623958268
            ],
            [
              113.57841968536377,
              22.13899623958268
            ],
            [
              113.57845187187195,
              22.138914252508958
            ],
            [
              113.57859402894974,
              22.139008661862405
            ],
            [
              113.57863157987595,
              22.138904314678612
            ],
            [
              113.57887297868729,
              22.13913536905309
            ],
            [
              113.57823997735976,
              22.139915485323222
            ],
            [
              113.57821851968765,
              22.140024800633693
            ],
            [
              113.57821851968765,
              22.14020616448434
            ],
            [
              113.57862353324889,
              22.1405192029099
            ],
            [
              113.58257442712784,
              22.143050813494018
            ],
            [
              113.58313500881194,
              22.143142735691246
            ],
            [
              113.58338445425034,
              22.143093048024518
            ],
            [
              113.58360975980759,
              22.14300857895084
            ],
            [
              113.58369290828705,
              22.142941500532718
            ],
            [
              113.58367681503296,
              22.1428843596328
            ],
            [
              113.5834863781929,
              22.142553935713337
            ],
            [
              113.58326375484467,
              22.14206202498324
            ],
            [
              113.5834166407585,
              22.142014821337963
            ],
            [
              113.58343005180359,
              22.14205208737502
            ],
            [
              113.58404159545897,
              22.141811100161043
            ],
            [
              113.58403354883194,
              22.14174402117243
            ],
            [
              113.58413279056549,
              22.141681910969297
            ],
            [
              113.5840979218483,
              22.14163470719661
            ],
            [
              113.58399868011475,
              22.14167197333426
            ],
            [
              113.58396381139754,
              22.141612347509273
            ],
            [
              113.58336299657822,
              22.141835944222784
            ],
            [
              113.5833603143692,
              22.141895569953093
            ],
            [
              113.5832181572914,
              22.141935320425937
            ],
            [
              113.58294725418091,
              22.141222294614636
            ],
            [
              113.58275413513182,
              22.140993728085153
            ],
            [
              113.58015775680542,
              22.138529161069567
            ],
            [
              113.58011484146117,
              22.13854655231856
            ],
            [
              113.58007460832594,
              22.138506800889118
            ],
            [
              113.5800638794899,
              22.138424813530456
            ],
            [
              113.58057618141174,
              22.13771922338002
            ],
            [
              113.58061373233795,
              22.137177606007157
            ],
            [
              113.58036696910858,
              22.135532865255794
            ],
            [
              113.5805332660675,
              22.135483174903992
            ],
            [
              113.58069956302641,
              22.135637214937518
            ],
            [
              113.58079612255096,
              22.135587524622522
            ],
            [
              113.58082294464111,
              22.13549808201136
            ],
            [
              113.58074247837067,
              22.135423546458686
            ],
            [
              113.58074247837067,
              22.135329134701987
            ],
            [
              113.58080685138702,
              22.135204908609936
            ],
            [
              113.58126282691954,
              22.135016084740176
            ],
            [
              113.58207285404205,
              22.135284413321465
            ],
            [
              113.58209431171417,
              22.135453360684487
            ],
            [
              113.5822069644928,
              22.13558255559005
            ],
            [
              113.58241081237792,
              22.135686905234984
            ],
            [
              113.58231961727142,
              22.13577137870042
            ],
            [
              113.58241617679596,
              22.13605958190716
            ],
            [
              113.582603931427,
              22.13624840437802
            ],
            [
              113.58243763446808,
              22.13656145160093
            ],
            [
              113.5826951265335,
              22.136854622178745
            ],
            [
              113.58284533023834,
              22.136859591166335
            ],
            [
              113.58296871185303,
              22.13636269154004
            ],
            [
              113.58293116092682,
              22.13624840437802
            ],
            [
              113.58289897441864,
              22.136084426983572
            ],
            [
              113.58302772045135,
              22.135994984687958
            ],
            [
              113.58292043209076,
              22.135567648491616
            ],
            [
              113.5829097032547,
              22.135463298758353
            ],
            [
              113.58315110206604,
              22.13535894894779
            ],
            [
              113.58314037322998,
              22.13520987765573
            ],
            [
              113.58316719532013,
              22.13497633231429
            ],
            [
              113.58393967151642,
              22.13512540385352
            ],
            [
              113.58419179916382,
              22.13547323683153
            ],
            [
              113.58558654785156,
              22.134509240469733
            ],
            [
              113.58636975288391,
              22.135522927186827
            ],
            [
              113.586745262146,
              22.135249630015686
            ],
            [
              113.58678281307219,
              22.135344041825675
            ],
            [
              113.58689546585083,
              22.13535894894779
            ],
            [
              113.58785569667816,
              22.134703034082612
            ],
            [
              113.58853697776794,
              22.135557710425118
            ],
            [
              113.58861207962036,
              22.13549808201136
            ],
            [
              113.58792006969452,
              22.13466328156836
            ],
            [
              113.58797371387482,
              22.134568869302086
            ],
            [
              113.58752310276031,
              22.13399742528716
            ],
            [
              113.58800053596497,
              22.133699279663443
            ],
            [
              113.58936846256256,
              22.135512989117174
            ],
            [
              113.58959376811981,
              22.13534901086656
            ],
            [
              113.58988881111145,
              22.135726657460324
            ],
            [
              113.58971178531647,
              22.135721688432778
            ],
            [
              113.58954548835754,
              22.13576640967445
            ],
            [
              113.58955085277557,
              22.135826037974606
            ],
            [
              113.58957231044769,
              22.13581113090192
            ],
            [
              113.58968228101729,
              22.13575647162197
            ],
            [
              113.58969032764435,
              22.13577634772624
            ],
            [
              113.58974665403366,
              22.135781316751867
            ],
            [
              113.58973324298859,
              22.135751502595465
            ],
            [
              113.5898619890213,
              22.13576640967445
            ],
            [
              113.58984053134918,
              22.135816099926327
            ],
            [
              113.5902053117752,
              22.13579870834016
            ],
            [
              113.59021604061127,
              22.135746533568792
            ],
            [
              113.59030991792679,
              22.135751502595465
            ],
            [
              113.59030991792679,
              22.135768894187446
            ],
            [
              113.59035819768906,
              22.13576640967445
            ],
            [
              113.59036087989807,
              22.135749018082148
            ],
            [
              113.59046280384064,
              22.135783801264612
            ],
            [
              113.59046816825865,
              22.135803677365
            ],
            [
              113.59051644802094,
              22.135791254802577
            ],
            [
              113.59051376581192,
              22.135749018082148
            ],
            [
              113.59046012163162,
              22.135758956135145
            ],
            [
              113.59036087989807,
              22.135721688432778
            ],
            [
              113.58995050191879,
              22.135736595514903
            ],
            [
              113.58996659517287,
              22.135711750377144
            ],
            [
              113.58965009450912,
              22.135311743055695
            ],
            [
              113.58998268842697,
              22.135105527657398
            ],
            [
              113.58990490436553,
              22.13500117758178
            ],
            [
              113.59037697315216,
              22.1347005495508
            ],
            [
              113.59042793512343,
              22.13474278658562
            ],
            [
              113.59064251184464,
              22.134665766100838
            ],
            [
              113.59073370695114,
              22.134412343563312
            ],
            [
              113.59072029590607,
              22.134243394951667
            ],
            [
              113.5905647277832,
              22.1339179198492
            ],
            [
              113.59057009220122,
              22.133828476177857
            ],
            [
              113.59127283096312,
              22.132417246290856
            ],
            [
              113.59234303236006,
              22.13288434507226
            ],
            [
              113.59186023473738,
              22.133798661608136
            ],
            [
              113.59191656112671,
              22.1338334452722
            ],
            [
              113.59244227409361,
              22.132832169221388
            ],
            [
              113.59130501747131,
              22.132352647401305
            ],
            [
              113.59188705682755,
              22.13123458500449
            ],
            [
              113.59232425689697,
              22.13137123755119
            ],
            [
              113.59240472316742,
              22.131338937870307
            ],
            [
              113.5924744606018,
              22.13121222366605
            ],
            [
              113.59254419803618,
              22.130866864766038
            ],
            [
              113.59252005815506,
              22.130514051202614
            ],
            [
              113.59239399433136,
              22.130228321260777
            ],
            [
              113.59238862991333,
              22.130104090670542
            ],
            [
              113.59246641397476,
              22.130019613806606
            ],
            [
              113.59259516000748,
              22.129763698292027
            ],
            [
              113.59254419803618,
              22.129619590321944
            ],
            [
              113.5925817489624,
              22.129552505526988
            ],
            [
              113.59251469373703,
              22.12921211181586
            ],
            [
              113.5924556851387,
              22.129154965345787
            ],
            [
              113.5924181342125,
              22.129192234785425
            ],
            [
              113.59240204095839,
              22.12915993460498
            ],
            [
              113.5924181342125,
              22.129097818852532
            ],
            [
              113.59237253665924,
              22.12905309549382
            ],
            [
              113.59239935874939,
              22.12900340285637
            ],
            [
              113.59230548143387,
              22.12895122556819
            ],
            [
              113.59224915504456,
              22.128993464326783
            ],
            [
              113.59215259552002,
              22.1289636487338
            ],
            [
              113.59178245067596,
              22.128973587265488
            ],
            [
              113.59172612428665,
              22.129020795281466
            ],
            [
              113.59185755252837,
              22.12915744997541
            ],
            [
              113.59177440404892,
              22.129169873122823
            ],
            [
              113.59141230583191,
              22.128876686551564
            ],
            [
              113.5913023352623,
              22.12881705530986
            ],
            [
              113.59121650457382,
              22.128839417028452
            ],
            [
              113.59039038419724,
              22.12839466662534
            ],
            [
              113.59032869338988,
              22.1283250966029
            ],
            [
              113.59030723571776,
              22.12824558796378
            ],
            [
              113.59054327011108,
              22.128235649380724
            ],
            [
              113.59057813882828,
              22.128126324920967
            ],
            [
              113.59056740999222,
              22.12799215387714
            ],
            [
              113.59005510807037,
              22.127316327417603
            ],
            [
              113.58990222215652,
              22.127184640266897
            ],
            [
              113.58941942453383,
              22.127117554312626
            ],
            [
              113.58915120363235,
              22.127115069647036
            ],
            [
              113.58853429555892,
              22.127219425563947
            ],
            [
              113.58839213848113,
              22.127192094259847
            ],
            [
              113.58796566724777,
              22.12744056046581
            ],
            [
              113.58797907829285,
              22.127597093950634
            ],
            [
              113.58808100223541,
              22.127753627261544
            ],
            [
              113.58796298503876,
              22.127666664332498
            ],
            [
              113.58778327703476,
              22.127602063264764
            ],
            [
              113.58768939971922,
              22.127609517235626
            ],
            [
              113.58748018741608,
              22.127711388131285
            ],
            [
              113.58682036399841,
              22.12759957860771
            ],
            [
              113.58635365962982,
              22.127793381725514
            ],
            [
              113.58634024858473,
              22.127880344576358
            ],
            [
              113.5859727859497,
              22.12793500691226
            ],
            [
              113.58548730611801,
              22.127644302427782
            ],
            [
              113.585304915905,
              22.127378443955408
            ],
            [
              113.58483821153641,
              22.127221910227693
            ],
            [
              113.58458071947098,
              22.126913811589027
            ],
            [
              113.5841166973114,
              22.126657890433442
            ],
            [
              113.58344078063965,
              22.12526149691242
            ],
            [
              113.58331203460693,
              22.125022965674603
            ],
            [
              113.58183145523071,
              22.12442663581375
            ],
            [
              113.58039379119873,
              22.123571891946153
            ],
            [
              113.58032941818237,
              22.123333357848605
            ],
            [
              113.5791492462158,
              22.12375079225438
            ],
            [
              113.57786178588867,
              22.12371103664994
            ],
            [
              113.57762306928635,
              22.123820364535128
            ],
            [
              113.57742190361023,
              22.12407629084381
            ],
            [
              113.57590377330779,
              22.12478940344638
            ],
            [
              113.57575625181198,
              22.125022965674603
            ],
            [
              113.57551753520966,
              22.125186955943974
            ],
            [
              113.57548266649245,
              22.125358400112432
            ],
            [
              113.57477188110352,
              22.125149685444967
            ],
            [
              113.57292652130127,
              22.123740853354324
            ],
            [
              113.57264757156372,
              22.1234228081825
            ],
            [
              113.57123136520384,
              22.121613912618795
            ],
            [
              113.57064127922058,
              22.120132986330667
            ],
            [
              113.569997549057,
              22.118373744950524
            ],
            [
              113.57006192207335,
              22.11713132961881
            ],
            [
              113.57014775276184,
              22.116644299821512
            ],
            [
              113.57040524482726,
              22.116346117482607
            ],
            [
              113.57060909271239,
              22.116306359789764
            ],
            [
              113.57102751731873,
              22.11655484518606
            ],
            [
              113.57107043266295,
              22.116395814582894
            ],
            [
              113.57077002525328,
              22.11617714721062
            ],
            [
              113.57151567935944,
              22.116333693204794
            ],
            [
              113.57204407453537,
              22.116303874933596
            ],
            [
              113.57300430536269,
              22.116172177493667
            ],
            [
              113.57309818267822,
              22.11629642036481
            ],
            [
              113.57321888208389,
              22.11638090545464
            ],
            [
              113.57344150543213,
              22.11628648093915
            ],
            [
              113.57381165027617,
              22.11568514438302
            ],
            [
              113.57399940490723,
              22.115705023318426
            ],
            [
              113.57402890920639,
              22.115575810188172
            ],
            [
              113.57414424419403,
              22.11548883974537
            ],
            [
              113.5739403963089,
              22.114974470601002
            ],
            [
              113.57393771409988,
              22.11498689499859
            ],
            [
              113.57401281595229,
              22.11488501490609
            ],
            [
              113.57402890920639,
              22.11454210088313
            ],
            [
              113.57393503189087,
              22.114097305364535
            ],
            [
              113.57409596443176,
              22.1141867615592
            ],
            [
              113.57427567243576,
              22.1140724564115
            ],
            [
              113.57422471046448,
              22.11386620993229
            ],
            [
              113.57401549816132,
              22.11368729707945
            ],
            [
              113.57366681098938,
              22.113617719797602
            ],
            [
              113.57367217540741,
              22.11339904811686
            ],
            [
              113.57342004776001,
              22.11336425940911
            ],
            [
              113.57324302196503,
              22.11320522520724
            ],
            [
              113.57322692871092,
              22.11259393582409
            ],
            [
              113.57218086719513,
              22.112569086606126
            ],
            [
              113.57211649417876,
              22.112434900753446
            ],
            [
              113.57187509536742,
              22.11248459923229
            ],
            [
              113.57174634933472,
              22.11224604637409
            ],
            [
              113.57130110263824,
              22.11204725201731
            ],
            [
              113.57113480567932,
              22.11207210132723
            ],
            [
              113.57074320316315,
              22.111783849062927
            ],
            [
              113.57058227062225,
              22.111843487510786
            ],
            [
              113.5699814558029,
              22.111659602215557
            ],
            [
              113.56946110725403,
              22.11166457209155
            ],
            [
              113.56885492801665,
              22.111793788805983
            ],
            [
              113.5676372051239,
              22.11228083535771
            ],
            [
              113.56744408607481,
              22.11226592579434
            ],
            [
              113.5673475265503,
              22.11200749311233
            ],
            [
              113.56543779373169,
              22.111977673926233
            ],
            [
              113.56535732746124,
              22.11209198077202
            ],
            [
              113.56618881225586,
              22.112131739653183
            ],
            [
              113.56616199016571,
              22.112236106662902
            ],
            [
              113.56608152389526,
              22.112315624332737
            ],
            [
              113.56575429439543,
              22.112325564038326
            ],
            [
              113.56560409069061,
              22.112390172107496
            ],
            [
              113.5653680562973,
              22.11240508165772
            ],
            [
              113.56530904769896,
              22.112295744919496
            ],
            [
              113.56516420841217,
              22.11228083535771
            ],
            [
              113.56501400470734,
              22.112101920493362
            ],
            [
              113.5648638010025,
              22.11198761365563
            ],
            [
              113.564413189888,
              22.11198264379102
            ],
            [
              113.56420934200287,
              22.112116830074054
            ],
            [
              113.56386065483092,
              22.112236106662902
            ],
            [
              113.56338322162628,
              22.111923005402012
            ],
            [
              113.56302917003632,
              22.11185342724963
            ],
            [
              113.56271803379059,
              22.111903125933416
            ],
            [
              113.56227278709412,
              22.111719240715956
            ],
            [
              113.56186509132384,
              22.111768939447018
            ],
            [
              113.56172025203705,
              22.11218640809648
            ],
            [
              113.56151103973389,
              22.11224107651858
            ],
            [
              113.56146812438965,
              22.112454780147083
            ],
            [
              113.56139302253723,
              22.11250944846514
            ],
            [
              113.56145203113556,
              22.11296667356812
            ],
            [
              113.56130719184875,
              22.11300146237396
            ],
            [
              113.56137692928314,
              22.113230074313098
            ],
            [
              113.56095314025879,
              22.11332947069276
            ],
            [
              113.5604864358902,
              22.113299651786228
            ],
            [
              113.55995535850525,
              22.113227589402708
            ],
            [
              113.55947256088257,
              22.112951764077273
            ],
            [
              113.55900585651396,
              22.112571571528118
            ],
            [
              113.55886369943617,
              22.11238768718231
            ],
            [
              113.55872690677643,
              22.112002523248407
            ],
            [
              113.55911046266556,
              22.113505899094136
            ],
            [
              113.55881005525589,
              22.111860882053318
            ],
            [
              113.55881005525589,
              22.11173166540037
            ],
            [
              113.55870544910431,
              22.111575114296812
            ],
            [
              113.55850964784622,
              22.11147571668055
            ],
            [
              113.55842918157578,
              22.11152044561654
            ],
            [
              113.55828434228897,
              22.111301770683514
            ],
            [
              113.55813682079314,
              22.11145583714889
            ],
            [
              113.55793833732604,
              22.111386258766018
            ],
            [
              113.55767011642456,
              22.11104830613229
            ],
            [
              113.55743408203124,
              22.111157643837707
            ],
            [
              113.55695128440856,
              22.110864419800198
            ],
            [
              113.55692982673644,
              22.110685503138825
            ],
            [
              113.55721414089203,
              22.110536405747617
            ],
            [
              113.55698347091675,
              22.110133842004018
            ],
            [
              113.55648994445801,
              22.10977103665804
            ],
            [
              113.5562002658844,
              22.109925104795696
            ],
            [
              113.55611979961395,
              22.109885345292405
            ],
            [
              113.5554438829422,
              22.11000462376863
            ],
            [
              113.55500936508179,
              22.10980582625222
            ],
            [
              113.5541832447052,
              22.109959894351864
            ],
            [
              113.5538774728775,
              22.110079172765026
            ],
            [
              113.5537701845169,
              22.110233240566068
            ],
            [
              113.5537326335907,
              22.110501616333657
            ],
            [
              113.55303525924683,
              22.11077993140506
            ],
            [
              113.55290114879607,
              22.11070538277907
            ],
            [
              113.55278849601746,
              22.110919088734786
            ],
            [
              113.55270802974701,
              22.11082963046715
            ],
            [
              113.55230569839478,
              22.11097375764818
            ],
            [
              113.55222523212433,
              22.111078125514904
            ],
            [
              113.5520589351654,
              22.111172553518244
            ],
            [
              113.55195701122284,
              22.111326620124796
            ],
            [
              113.55192482471466,
              22.11149559620941
            ],
            [
              113.5516083240509,
              22.11160493356803
            ],
            [
              113.55139374732971,
              22.111445897382016
            ],
            [
              113.55120599269867,
              22.11155523477916
            ],
            [
              113.55117380619049,
              22.11172421058984
            ],
            [
              113.551087975502,
              22.111833547771216
            ],
            [
              113.55076611042021,
              22.111818638160575
            ],
            [
              113.55062663555144,
              22.111709300967647
            ],
            [
              113.55017602443695,
              22.11215658894822
            ],
            [
              113.54995608329773,
              22.112181438238867
            ],
            [
              113.54972541332245,
              22.113274802692622
            ],
            [
              113.54929625988005,
              22.113667417859578
            ],
            [
              113.5492157936096,
              22.113657478248587
            ],
            [
              113.54911386966704,
              22.11379166293786
            ],
            [
              113.54941964149475,
              22.11408985067909
            ],
            [
              113.5493767261505,
              22.114204155812697
            ],
            [
              113.54979515075684,
              22.114393007569557
            ],
            [
              113.5500955581665,
              22.114661375420493
            ],
            [
              113.5505998134613,
              22.116018116181404
            ],
            [
              113.55097532272339,
              22.117528903716238
            ],
            [
              113.55088949203491,
              22.117976173235665
            ],
            [
              113.55034232139586,
              22.117807204917316
            ],
            [
              113.5503852367401,
              22.118314109264773
            ],
            [
              113.55051398277283,
              22.118403562783943
            ],
            [
              113.5502564907074,
              22.118652044483785
            ],
            [
              113.55012774467468,
              22.118572530387492
            ],
            [
              113.54985952377318,
              22.118691801515123
            ],
            [
              113.54987025260925,
              22.119009857362137
            ],
            [
              113.54985952377318,
              22.11905955352341
            ],
            [
              113.54935526847838,
              22.1189701004205
            ],
            [
              113.5493767261505,
              22.11879119404441
            ],
            [
              113.54926943778992,
              22.11875143704111
            ],
            [
              113.54923725128174,
              22.119009857362137
            ],
            [
              113.54965031147003,
              22.119074462368378
            ],
            [
              113.54963421821594,
              22.11921858112175
            ],
            [
              113.54979246854782,
              22.11922603553601
            ],
            [
              113.54980051517485,
              22.119531666181707
            ],
            [
              113.54970127344131,
              22.119611179737
            ],
            [
              113.54972809553146,
              22.119755297941662
            ],
            [
              113.54984074831007,
              22.11972796519003
            ],
            [
              113.54999095201492,
              22.1202000756097
            ],
            [
              113.54979246854782,
              22.120272134429406
            ],
            [
              113.54985415935516,
              22.12049079544992
            ],
            [
              113.5501679778099,
              22.120408797606967
            ],
            [
              113.55019479990005,
              22.12045103892597
            ],
            [
              113.5500231385231,
              22.120485825885037
            ],
            [
              113.55005532503128,
              22.120719395245054
            ],
            [
              113.55034500360487,
              22.120704486574063
            ],
            [
              113.55040669441223,
              22.120741758248577
            ],
            [
              113.55026185512541,
              22.120823755897835
            ],
            [
              113.55040937662125,
              22.120935570797222
            ],
            [
              113.55058908462524,
              22.120774060358524
            ],
            [
              113.55074733495711,
              22.120863512316664
            ],
            [
              113.55074733495711,
              22.120923146923875
            ],
            [
              113.55090558528899,
              22.12099520537395
            ],
            [
              113.55086266994476,
              22.12106477901492
            ],
            [
              113.55118453502655,
              22.12120144142398
            ],
            [
              113.55145543813705,
              22.121447433426408
            ],
            [
              113.55174243450165,
              22.121606458330806
            ],
            [
              113.55178534984589,
              22.12226491891608
            ],
            [
              113.55150908231735,
              22.12267738699872
            ],
            [
              113.55141520500183,
              22.12519192534309
            ],
            [
              113.55153322219847,
              22.125241619324676
            ],
            [
              113.55153322219847,
              22.12541057873101
            ],
            [
              113.55138301849365,
              22.125460272635504
            ],
            [
              113.55144739151001,
              22.127676602955685
            ],
            [
              113.55159759521484,
              22.128372304836166
            ],
            [
              113.55139374732971,
              22.12836236626205
            ],
            [
              113.55120062828064,
              22.128710215938696
            ],
            [
              113.5511040687561,
              22.129316466179677
            ],
            [
              113.55137228965758,
              22.12963449804984
            ],
            [
              113.55150103569031,
              22.13015129830773
            ],
            [
              113.55180144309998,
              22.130340128698325
            ],
            [
              113.55183362960814,
              22.144601060899692
            ],
            [
              113.54910850524902,
              22.148317610159744
            ],
            [
              113.54938745498657,
              22.14839710746777
            ],
            [
              113.54947328567505,
              22.148118866693284
            ],
            [
              113.5500955581665,
              22.14813874105255
            ],
            [
              113.55000972747803,
              22.15121923281353
            ],
            [
              113.5480785369873,
              22.151239106735037
            ],
            [
              113.54764938354492,
              22.150960871578597
            ],
            [
              113.54932308197021,
              22.148874090373027
            ],
            [
              113.54885101318358,
              22.14859585054139
            ],
            [
              113.54561090469359,
              22.152113556502893
            ],
            [
              113.54230642318724,
              22.154558012256906
            ],
            [
              113.54172706604004,
              22.155293328037825
            ],
            [
              113.53996753692627,
              22.16008272328465
            ],
            [
              113.53958129882812,
              22.162030231568444
            ],
            [
              113.53940963745117,
              22.163858480114076
            ],
            [
              113.53880882263184,
              22.165726448648883
            ],
            [
              113.53893756866455,
              22.1661238855618
            ],
            [
              113.53915214538574,
              22.166163629191324
            ],
            [
              113.53368043899536,
              22.177052960478665
            ],
            [
              113.53280067443848,
              22.17830478209933
            ],
            [
              113.5321569442749,
              22.179079713705825
            ],
            [
              113.5321569442749,
              22.179457242940636
            ],
            [
              113.53217571973799,
              22.179489531578124
            ],
            [
              113.53171706199646,
              22.179874510915035
            ],
            [
              113.5317251086235,
              22.17973790546459
            ],
            [
              113.531813621521,
              22.179693198197413
            ],
            [
              113.53188335895538,
              22.17961371857621
            ],
            [
              113.53189677000046,
              22.179524303948646
            ],
            [
              113.53185921907425,
              22.17942743803793
            ],
            [
              113.5317599773407,
              22.17935789324032
            ],
            [
              113.5316526889801,
              22.179367828213522
            ],
            [
              113.53154808282851,
              22.179442340490073
            ],
            [
              113.53151589632034,
              22.179509401505182
            ],
            [
              113.53152394294739,
              22.179623653531323
            ],
            [
              113.5315990447998,
              22.179688230722405
            ],
            [
              113.53167146444319,
              22.179730454254386
            ],
            [
              113.53167951107025,
              22.17990928319032
            ],
            [
              113.53138983249663,
              22.18015765633497
            ],
            [
              113.53086680173874,
              22.180396094140853
            ],
            [
              113.53051543235779,
              22.180614661774214
            ],
            [
              113.53027939796446,
              22.180835712784937
            ],
            [
              113.52995216846466,
              22.181238074406398
            ],
            [
              113.5299414396286,
              22.181339906485942
            ],
            [
              113.52976441383362,
              22.18159572821389
            ],
            [
              113.52962762117386,
              22.181737299261233
            ],
            [
              113.52905094623564,
              22.1827282925991
            ],
            [
              113.52887392044067,
              22.18327470197679
            ],
            [
              113.5287156701088,
              22.184012351266265
            ],
            [
              113.52876663208008,
              22.184148952561582
            ],
            [
              113.52871835231781,
              22.184434573022656
            ],
            [
              113.52878272533417,
              22.184764898570986
            ],
            [
              113.52887660264969,
              22.185072870563143
            ],
            [
              113.52907508611679,
              22.18554476182215
            ],
            [
              113.52948546409607,
              22.186158218089407
            ],
            [
              113.52995753288268,
              22.18660775316765
            ],
            [
              113.5302472114563,
              22.18680892585834
            ],
            [
              113.53059321641922,
              22.186985262177465
            ],
            [
              113.53016674518585,
              22.18768812164455
            ],
            [
              113.5302284359932,
              22.18779491623816
            ],
            [
              113.53041887283325,
              22.18770053962472
            ],
            [
              113.53051275014877,
              22.18782968655345
            ],
            [
              113.5303544998169,
              22.187933997447672
            ],
            [
              113.53040814399719,
              22.188038308264446
            ],
            [
              113.53011846542357,
              22.188167454882674
            ],
            [
              113.53082925081253,
              22.189225459246114
            ],
            [
              113.53092849254608,
              22.189235393521617
            ],
            [
              113.53113234043121,
              22.189096313600547
            ],
            [
              113.53115648031235,
              22.189138534305435
            ],
            [
              113.53105187416077,
              22.18922794281506
            ],
            [
              113.53156417608261,
              22.189888570594736
            ],
            [
              113.53169292211533,
              22.189789228269962
            ],
            [
              113.53207379579543,
              22.190295873391857
            ],
            [
              113.53226691484451,
              22.1901692122827
            ],
            [
              113.53262901306152,
              22.190663438316893
            ],
            [
              113.53235542774199,
              22.190901858294506
            ],
            [
              113.53436708450317,
              22.19330590378817
            ],
            [
              113.53448510169983,
              22.193226431867537
            ],
            [
              113.53472650051117,
              22.193698295737157
            ],
            [
              113.53481769561768,
              22.193648625930813
            ],
            [
              113.53493571281433,
              22.193817503200744
            ],
            [
              113.53481233119963,
              22.19386220597352
            ],
            [
              113.53504300117493,
              22.194542679757564
            ],
            [
              113.53552579879761,
              22.194378770315396
            ],
            [
              113.53555798530577,
              22.194443340724558
            ],
            [
              113.53538632392883,
              22.194507911104
            ],
            [
              113.53547215461731,
              22.194622150933377
            ],
            [
              113.53556334972382,
              22.194552613657
            ],
            [
              113.53562235832214,
              22.194607250091344
            ],
            [
              113.5351288318634,
              22.194751291498182
            ],
            [
              113.53535950183868,
              22.19527778641793
            ],
            [
              113.53544533252716,
              22.19526785256979
            ],
            [
              113.5356330871582,
              22.195784411741315
            ],
            [
              113.53550970554352,
              22.195794345552933
            ],
            [
              113.53563845157622,
              22.196281101460492
            ],
            [
              113.53585839271544,
              22.19621653189634
            ],
            [
              113.53593349456787,
              22.196340704108728
            ],
            [
              113.53581547737122,
              22.196385406078324
            ],
            [
              113.53584229946136,
              22.19642017426704
            ],
            [
              113.53546679019928,
              22.196524478781555
            ],
            [
              113.53584229946136,
              22.197979767021565
            ],
            [
              113.53630363941191,
              22.19785062942577
            ],
            [
              113.53629291057587,
              22.197905264576953
            ],
            [
              113.53611588478088,
              22.197925131899378
            ],
            [
              113.53611588478088,
              22.198019501642538
            ],
            [
              113.53635728359222,
              22.197940032389358
            ],
            [
              113.53636801242828,
              22.19804930260086
            ],
            [
              113.53615880012512,
              22.198079103552885
            ],
            [
              113.536137342453,
              22.198153605905265
            ],
            [
              113.53640019893646,
              22.19810393767473
            ],
            [
              113.53638410568236,
              22.198168506370997
            ],
            [
              113.536137342453,
              22.19821817457868
            ],
            [
              113.53630363941191,
              22.199037697468878
            ],
            [
              113.53646993637085,
              22.199007896720307
            ],
            [
              113.53654503822325,
              22.199226435396216
            ],
            [
              113.53665769100189,
              22.199231402180356
            ],
            [
              113.53670597076415,
              22.1993506049469
            ],
            [
              113.53661477565765,
              22.199380405622726
            ],
            [
              113.53661477565765,
              22.199559209544834
            ],
            [
              113.53675961494446,
              22.199534375680383
            ],
            [
              113.53681862354279,
              22.199747946771144
            ],
            [
              113.53663623332977,
              22.19977774736263
            ],
            [
              113.53668451309203,
              22.199896949665323
            ],
            [
              113.53673815727234,
              22.199896949665323
            ],
            [
              113.53679180145264,
              22.199891982904735
            ],
            [
              113.5368400812149,
              22.20002111862301
            ],
            [
              113.53650212287903,
              22.200055885911492
            ],
            [
              113.53673279285431,
              22.200939965496843
            ],
            [
              113.53700637817383,
              22.200900231702366
            ],
            [
              113.53704929351805,
              22.201014466331156
            ],
            [
              113.53695809841156,
              22.20104426665381
            ],
            [
              113.53699028491974,
              22.20119823488676
            ],
            [
              113.53709757328033,
              22.2011684345968
            ],
            [
              113.53714048862457,
              22.20145153709615
            ],
            [
              113.537038564682,
              22.201461470506814
            ],
            [
              113.5370922088623,
              22.201595571481967
            ],
            [
              113.53713512420654,
              22.201580671379947
            ],
            [
              113.53721022605895,
              22.2018339728993
            ],
            [
              113.5370546579361,
              22.201843906282903
            ],
            [
              113.53707075119019,
              22.20200780701087
            ],
            [
              113.53691518306732,
              22.20203760712268
            ],
            [
              113.5371458530426,
              22.20324947297645
            ],
            [
              113.53751599788666,
              22.203179939972664
            ],
            [
              113.5373443365097,
              22.203299139386623
            ],
            [
              113.5374730825424,
              22.20346800504981
            ],
            [
              113.53723168373106,
              22.203413372063363
            ],
            [
              113.53715121746062,
              22.20361700399569
            ],
            [
              113.53729069232939,
              22.204342129941203
            ],
            [
              113.53746771812439,
              22.204635159226314
            ],
            [
              113.53765547275543,
              22.204734491048544
            ],
            [
              113.53808999061584,
              22.20481892304217
            ],
            [
              113.5384064912796,
              22.204491127959226
            ],
            [
              113.53869080543518,
              22.204565626908945
            ],
            [
              113.53850841522217,
              22.205027519514573
            ],
            [
              113.53861033916473,
              22.205042419250738
            ],
            [
              113.53874981403351,
              22.204605359665948
            ],
            [
              113.53911995887756,
              22.20468979173724
            ],
            [
              113.53894829750061,
              22.20510201817958
            ],
            [
              113.53906631469727,
              22.205136784209735
            ],
            [
              113.53921115398407,
              22.204684825146227
            ],
            [
              113.53956520557402,
              22.204769257169723
            ],
            [
              113.53942036628723,
              22.205206316244187
            ],
            [
              113.53950083255768,
              22.205231149105284
            ],
            [
              113.5396295785904,
              22.204799056695308
            ],
            [
              113.54045569896698,
              22.205007653197228
            ],
            [
              113.54043424129485,
              22.205062285563173
            ],
            [
              113.54024112224579,
              22.205002686617444
            ],
            [
              113.5400640964508,
              22.20553410965693
            ],
            [
              113.5398656129837,
              22.205544042778698
            ],
            [
              113.5398119688034,
              22.20560364149456
            ],
            [
              113.54001581668854,
              22.205673173297747
            ],
            [
              113.53998363018036,
              22.205737738512706
            ],
            [
              113.53945791721344,
              22.20557880869936
            ],
            [
              113.539377450943,
              22.20578740404248
            ],
            [
              113.5396295785904,
              22.205832103004237
            ],
            [
              113.53957056999207,
              22.205931433979405
            ],
            [
              113.53884100914,
              22.205722838850356
            ],
            [
              113.53877663612366,
              22.205802303697983
            ],
            [
              113.5375428199768,
              22.20541491214087
            ],
            [
              113.53695273399353,
              22.205861902304164
            ],
            [
              113.536856174469,
              22.20599103253077
            ],
            [
              113.53689908981323,
              22.20643802085934
            ],
            [
              113.53701710700989,
              22.206537351405697
            ],
            [
              113.54186654090881,
              22.207878306901083
            ],
            [
              113.54087948799133,
              22.210738969135146
            ],
            [
              113.53923797607422,
              22.210212532199535
            ],
            [
              113.53922724723816,
              22.2100834058571
            ],
            [
              113.53994607925415,
              22.210262196145745
            ],
            [
              113.53998899459837,
              22.21010327145597
            ],
            [
              113.5396134853363,
              22.210003943433463
            ],
            [
              113.5397744178772,
              22.209527167946753
            ],
            [
              113.54020357131958,
              22.209626496306743
            ],
            [
              113.54024648666382,
              22.209527167946753
            ],
            [
              113.53980660438536,
              22.209427839516472
            ],
            [
              113.53990316390991,
              22.209129853803795
            ],
            [
              113.54032158851624,
              22.209239115305234
            ],
            [
              113.54033231735228,
              22.209169585268704
            ],
            [
              113.53678107261658,
              22.208166362335742
            ],
            [
              113.53675961494446,
              22.208096831767715
            ],
            [
              113.53605151176453,
              22.207848508029254
            ],
            [
              113.53601932525635,
              22.207977636428083
            ],
            [
              113.53591203689575,
              22.207957770528306
            ],
            [
              113.53597640991211,
              22.2078286421112
            ],
            [
              113.5349142551422,
              22.20744125614703
            ],
            [
              113.53474259376526,
              22.207530653002884
            ],
            [
              113.53413105010986,
              22.20972582459642
            ],
            [
              113.53329420089722,
              22.212050086503282
            ],
            [
              113.53326201438902,
              22.21221894163747
            ],
            [
              113.53333711624146,
              22.21240766184111
            ],
            [
              113.53438854217528,
              22.21309301202486
            ],
            [
              113.53502154350281,
              22.2133512590518
            ],
            [
              113.53582620620728,
              22.213510180062897
            ],
            [
              113.53666305541992,
              22.21361943815362
            ],
            [
              113.53796124458313,
              22.213599573052548
            ],
            [
              113.53879809379578,
              22.213450584704834
            ],
            [
              113.5400640964508,
              22.213222135597757
            ],
            [
              113.54121208190918,
              22.212944023139254
            ],
            [
              113.54160904884338,
              22.21318240528029
            ],
            [
              113.54194164276122,
              22.21412599728066
            ],
            [
              113.54215621948242,
              22.21464248705652
            ],
            [
              113.54232788085936,
              22.214771609203396
            ],
            [
              113.54233860969543,
              22.214930528605638
            ],
            [
              113.54244589805602,
              22.214980190881906
            ],
            [
              113.54251027107239,
              22.215377488459303
            ],
            [
              113.54271411895752,
              22.215605934056832
            ],
            [
              113.54266047477722,
              22.21566552849935
            ],
            [
              113.54313254356383,
              22.216400524542326
            ],
            [
              113.54446291923522,
              22.216976599829987
            ],
            [
              113.5452890396118,
              22.216926938260425
            ],
            [
              113.54560017585754,
              22.216758088792446
            ],
            [
              113.54699492454529,
              22.216758088792446
            ],
            [
              113.54826629161835,
              22.21671835947633
            ]
          ]
        ]
      }
    }
  ]
}
