{
  "type": "FeatureCollection",
  "features": [
    {
      "type": "Feature",
      "geometry": {
        "type": "Polygon",
        "coordinates": [
          [
            [
              113.546503,
              22.216778
            ],
            [
              113.546568,
              22.216763
            ],
            [
              113.546783,
              22.216763
            ],
            [
              113.547044,
              22.216763
            ],
            [
              113.547274,
              22.216683
            ],
            [
              113.547275,
              22.216677
            ],
            [
              113.547449,
              22.216614
            ],
            [
              113.54747,
              22.216607
            ],
            [
              113.547394,
              22.216492
            ],
            [
              113.547372,
              22.215885
            ],
            [
              113.547656,
              22.215961
            ],
            [
              113.547754,
              22.215988
            ],
            [
              113.547846,
              22.216011
            ],
            [
              113.54792,
              22.216022
            ],
            [
              113.547984,
              22.216028
            ],
            [
              113.548061,
              22.216032
            ],
            [
              113.548113,
              22.216033
            ],
            [
              113.548204,
              22.216033
            ],
            [
              113.54827,
              22.21603
            ],
            [
              113.548339,
              22.216024
            ],
            [
              113.548383,
              22.216018
            ],
            [
              113.548444,
              22.216008
            ],
            [
              113.548572,
              22.215986
            ],
            [
              113.548706,
              22.215961
            ],
            [
              113.548551,
              22.214976
            ],
            [
              113.548545,
              22.214941
            ],
            [
              113.548532,
              22.214863
            ],
            [
              113.548529,
              22.214839
            ],
            [
              113.548528,
              22.214828
            ],
            [
              113.548527,
              22.214817
            ],
            [
              113.548525,
              22.214806
            ],
            [
              113.548522,
              22.214799
            ],
            [
              113.548514,
              22.214791
            ],
            [
              113.54851,
              22.214789
            ],
            [
              113.548496,
              22.214782
            ],
            [
              113.548479,
              22.214773
            ],
            [
              113.548458,
              22.214763
            ],
            [
              113.548434,
              22.214751
            ],
            [
              113.548425,
              22.214746
            ],
            [
              113.548415,
              22.214741
            ],
            [
              113.548408,
              22.214738
            ],
            [
              113.548394,
              22.214731
            ],
            [
              113.548389,
              22.214729
            ],
            [
              113.548374,
              22.214614
            ],
            [
              113.54892,
              22.214539
            ],
            [
              113.548905,
              22.214448
            ],
            [
              113.548841,
              22.21407
            ],
            [
              113.548805,
              22.213855
            ],
            [
              113.548771,
              22.213653
            ],
            [
              113.548734,
              22.213434
            ],
            [
              113.548524,
              22.212198
            ],
            [
              113.548361,
              22.211233
            ],
            [
              113.54833,
              22.211051
            ],
            [
              113.548291,
              22.210816
            ],
            [
              113.548184,
              22.210186
            ],
            [
              113.54745,
              22.210265
            ],
            [
              113.547443,
              22.210266
            ],
            [
              113.546595,
              22.210365
            ],
            [
              113.545643,
              22.210476
            ],
            [
              113.544526,
              22.210606
            ],
            [
              113.544525,
              22.210607
            ],
            [
              113.544251,
              22.211488
            ],
            [
              113.544425,
              22.211479
            ],
            [
              113.544445,
              22.211743
            ],
            [
              113.544455,
              22.211908
            ],
            [
              113.544456,
              22.211968
            ],
            [
              113.544498,
              22.212032
            ],
            [
              113.544461,
              22.212256
            ],
            [
              113.544234,
              22.21233
            ],
            [
              113.544151,
              22.212357
            ],
            [
              113.544159,
              22.212361
            ],
            [
              113.543919,
              22.212445
            ],
            [
              113.543918,
              22.212445
            ],
            [
              113.543928,
              22.212596
            ],
            [
              113.543937,
              22.212679
            ],
            [
              113.543961,
              22.212907
            ],
            [
              113.543349,
              22.212697
            ],
            [
              113.542883,
              22.212554
            ],
            [
              113.542878,
              22.212547
            ],
            [
              113.54257,
              22.212452
            ],
            [
              113.542184,
              22.212401
            ],
            [
              113.54198,
              22.212412
            ],
            [
              113.54124,
              22.212454
            ],
            [
              113.541249,
              22.212614
            ],
            [
              113.541263,
              22.212852
            ],
            [
              113.54127,
              22.212974
            ],
            [
              113.541322,
              22.212978
            ],
            [
              113.541428,
              22.213029
            ],
            [
              113.541512,
              22.213086
            ],
            [
              113.541601,
              22.213162
            ],
            [
              113.541664,
              22.213227
            ],
            [
              113.541695,
              22.213244
            ],
            [
              113.5417,
              22.213222
            ],
            [
              113.541715,
              22.213224
            ],
            [
              113.54176,
              22.213302
            ],
            [
              113.541956,
              22.21364
            ],
            [
              113.541987,
              22.213667
            ],
            [
              113.542026,
              22.213674
            ],
            [
              113.542038,
              22.213689
            ],
            [
              113.542063,
              22.213723
            ],
            [
              113.542122,
              22.213812
            ],
            [
              113.542355,
              22.214165
            ],
            [
              113.54243,
              22.214281
            ],
            [
              113.542483,
              22.214428
            ],
            [
              113.542604,
              22.214671
            ],
            [
              113.542742,
              22.214951
            ],
            [
              113.54274,
              22.214952
            ],
            [
              113.542764,
              22.215001
            ],
            [
              113.542775,
              22.21502
            ],
            [
              113.542857,
              22.215187
            ],
            [
              113.542935,
              22.215347
            ],
            [
              113.543022,
              22.215523
            ],
            [
              113.543116,
              22.215713
            ],
            [
              113.54324,
              22.215963
            ],
            [
              113.543398,
              22.216286
            ],
            [
              113.543414,
              22.216308
            ],
            [
              113.543436,
              22.216326
            ],
            [
              113.543671,
              22.216484
            ],
            [
              113.543777,
              22.216555
            ],
            [
              113.543896,
              22.216633
            ],
            [
              113.543976,
              22.216684
            ],
            [
              113.544039,
              22.216724
            ],
            [
              113.54414,
              22.21679
            ],
            [
              113.544212,
              22.216838
            ],
            [
              113.544324,
              22.216913
            ],
            [
              113.544351,
              22.216931
            ],
            [
              113.544359,
              22.216934
            ],
            [
              113.544576,
              22.216928
            ],
            [
              113.544875,
              22.21692
            ],
            [
              113.544957,
              22.216917
            ],
            [
              113.545019,
              22.216914
            ],
            [
              113.545122,
              22.216908
            ],
            [
              113.545186,
              22.216902
            ],
            [
              113.545196,
              22.2169
            ],
            [
              113.545476,
              22.216792
            ],
            [
              113.545872,
              22.216788
            ],
            [
              113.546465,
              22.21678
            ],
            [
              113.546503,
              22.216778
            ]
          ]
        ]
      },
      "properties": {
        "nameCht": "台山區",
        "namePor": "Tamagnini Barbosa"
      }
    }
  ]
}