{
  "type": "FeatureCollection",
  "features": [
    {
      "type": "Feature",
      "geometry": {
        "type": "MultiLineString",
        "coordinates": [
          [
            [
              113.543116,
              22.193758
            ],
            [
              113.543155,
              22.193818
            ],
            [
              113.543165,
              22.193833
            ],
            [
              113.543186,
              22.193865
            ],
            [
              113.543076,
              22.193933
            ],
            [
              113.54312,
              22.194002
            ],
            [
              113.543124,
              22.194012
            ],
            [
              113.543118,
              22.194032
            ]
          ],
          [
            [
              113.543118,
              22.194032
            ],
            [
              113.543149,
              22.194168
            ]
          ],
          [
            [
              113.542991,
              22.194084
            ],
            [
              113.543053,
              22.19405
            ],
            [
              113.543077,
              22.194045
            ],
            [
              113.543118,
              22.194032
            ]
          ],
          [
            [
              113.543293,
              22.194145
            ],
            [
              113.543149,
              22.194168
            ]
          ],
          [
            [
              113.543149,
              22.194168
            ],
            [
              113.542942,
              22.194198
            ]
          ]
        ]
      },
      "properties": {
        "nameCht": "連丁里 / 連丁圍",
        "namePor": "Beco da Carpideira"
      }
    }
  ]
}
