{
  "type": "FeatureCollection",
  "features": [
    {
      "type": "Feature",
      "geometry": {
        "type": "MultiLineString",
        "coordinates": [
          [
            [
              113.558387,
              22.165252
            ],
            [
              113.55863,
              22.165334
            ],
            [
              113.558953,
              22.165148
            ],
            [
              113.559294,
              22.164689
            ],
            [
              113.55946,
              22.164549
            ],
            [
              113.560133,
              22.164366
            ],
            [
              113.560314,
              22.164288
            ],
            [
              113.560423,
              22.164203
            ],
            [
              113.56049,
              22.164079
            ],
            [
              113.560417,
              22.163719
            ],
            [
              113.560303,
              22.163433
            ],
            [
              113.560163,
              22.163213
            ],
            [
              113.56006,
              22.163092
            ],
            [
              113.560066,
              22.163003
            ],
            [
              113.560288,
              22.162708
            ]
          ]
        ]
      },
      "properties": {
        "nameCht": "聚龍街",
        "namePor": "Rua de Choi Long"
      }
    }
  ]
}
