{
  "type": "FeatureCollection",
  "features": [
    {
      "type": "Feature",
      "geometry": {
        "type": "MultiLineString",
        "coordinates": [
          [
            [
              113.552015,
              22.11638
            ],
            [
              113.551968,
              22.116344
            ],
            [
              113.551913,
              22.116302
            ],
            [
              113.551858,
              22.116262
            ],
            [
              113.551813,
              22.116246
            ],
            [
              113.551753,
              22.116226
            ],
            [
              113.551626,
              22.116204
            ]
          ]
        ]
      },
      "properties": {
        "nameCht": "情人街",
        "namePor": "Azinhaga dos Amores"
      }
    }
  ]
}
